dagster_cron/__init__.py
dagster_cron/cron_scheduler.py
dagster_cron/version.py
dagster_cron_tests/__init__.py
dagster_cron_tests/test_cron_scheduler.py
dagster_cron_tests/test_version.py
dagster_cron_tests/snapshots/__init__.py
dagster_cron_tests/snapshots/snap_test_cron_scheduler.py
dagster_cron-0.11.16.dist-info/LICENSE
dagster_cron-0.11.16.dist-info/METADATA
dagster_cron-0.11.16.dist-info/WHEEL
dagster_cron-0.11.16.dist-info/top_level.txt
dagster_cron-0.11.16.dist-info/RECORD
