Metadata-Version: 2.1
Name: dagster-cron
Version: 0.11.16
Summary: A Dagster integration for cron
Home-page: https://github.com/dagster-io/dagster/tree/master/python_modules/libraries/dagster-cron
Author: Elementl
Author-email: hello@elementl.com
License: Apache-2.0
Platform: UNKNOWN
Classifier: Programming Language :: Python :: 3.6
Classifier: Programming Language :: Python :: 3.7
Classifier: Programming Language :: Python :: 3.8
Classifier: License :: OSI Approved :: Apache Software License
Classifier: Operating System :: OS Independent
License-File: LICENSE
Requires-Dist: dagster (==0.11.16)
Requires-Dist: python-crontab (>=2.4.1)
